[
{"name": "Jewelry Sample", "pieces": "16", "minifigs": null, "image": "https://images.brickset.com/sets/small/1386-1.jpg?200801240244", "community": "30 own this set", "needs": ", 24 want it", "buy_at": "Amazon", "buy_at2": "Amazon", "buy_at3": "eBay", "buy_at4": "BrickLink"},
{"name": "Preschool Playtable", "pieces": "18", "minifigs": null, "image": "https://images.brickset.com/sets/small/3125-1.jpg?200406090151", "community": "41 own this set", "needs": ", 36 want it", "buy_at": "Amazon", "buy_at2": "Amazon", "buy_at3": "eBay", "buy_at4": "BrickLink"},
{"name": "Heart", "pieces": "9", "minifigs": null, "image": "https://images.brickset.com/sets/small/3194-1.jpg?200407270240", "community": "58 own this set", "needs": ", 27 want it", "buy_at": "Amazon", "buy_at2": "Amazon", "buy_at3": "eBay", "buy_at4": "BrickLink"},
{"name": "Daisy", "pieces": "9", "minifigs": null, "image": "https://images.brickset.com/sets/small/3195-1.jpg?200407270238", "community": "51 own this set", "needs": ", 28 want it", "buy_at": "Amazon", "buy_at2": "Amazon", "buy_at3": "eBay", "buy_at4": "BrickLink"},
{"name": "Star", "pieces": "9", "minifigs": null, "image": "https://images.brickset.com/sets/small/3196-1.jpg?200411200959", "community": "38 own this set", "needs": ", 29 want it", "buy_at": "Amazon", "buy_at2": "Amazon", "buy_at3": "eBay", "buy_at4": "BrickLink"},
{"name": "NHL Championship Challenge", "pieces": "374", "minifigs": "8", "image": "https://images.brickset.com/sets/small/3578-1.jpg?200401280454", "community": "347 own this set", "needs": ", 422 want it", "buy_at": "Amazon", "buy_at2": "Amazon", "buy_at3": "eBay", "buy_at4": "BrickLink"},
{"name": "NHL Street Hockey", "pieces": "114", "minifigs": "2", "image": "https://images.brickset.com/sets/small/3579-1.jpg?200401280454", "community": "284 own this set", "needs": ", 245 want it", "buy_at": "Amazon", "buy_at2": "Amazon", "buy_at3": "eBay", "buy_at4": "BrickLink"},
{"name": "Car", "pieces": null, "minifigs": null, "image": "/assets/images/misc/blankbox.gif", "community": null, "needs": "71 want this set", "buy_at": null, "buy_at2": null, "buy_at3": null, "buy_at4": null},
{"name": "Aeroplane", "pieces": null, "minifigs": null, "image": "/assets/images/misc/blankbox.gif", "community": null, "needs": "75 want this set", "buy_at": null, "buy_at2": null, "buy_at3": null, "buy_at4": null},
{"name": "Boat", "pieces": null, "minifigs": null, "image": "/assets/images/misc/blankbox.gif", "community": null, "needs": "71 want this set", "buy_at": null, "buy_at2": null, "buy_at3": null, "buy_at4": null},
{"name": "Space Plane", "pieces": null, "minifigs": null, "image": "/assets/images/misc/blankbox.gif", "community": null, "needs": "82 want this set", "buy_at": null, "buy_at2": null, "buy_at3": null, "buy_at4": null},
{"name": "Helicopter", "pieces": "9", "minifigs": null, "image": "https://images.brickset.com/sets/small/4037-1.jpg?201208280313", "community": "21 own this set", "needs": ", 114 want it", "buy_at": "Amazon", "buy_at2": "Amazon", "buy_at3": "eBay", "buy_at4": "BrickLink"},
{"name": "Yellow Racer", "pieces": "28", "minifigs": null, "image": "https://images.brickset.com/sets/small/4308-1.jpg?200801240223", "community": "315 own this set", "needs": ", 133 want it", "buy_at": "Amazon", "buy_at2": "Amazon", "buy_at3": "eBay", "buy_at4": "BrickLink"},
{"name": "Blue Racer", "pieces": "31", "minifigs": null, "image": "https://images.brickset.com/sets/small/4309-1.jpg?200801240224", "community": "446 own this set", "needs": ", 132 want it", "buy_at": "Amazon", "buy_at2": "Amazon", "buy_at3": "eBay", "buy_at4": "BrickLink"},
{"name": "Orange Racer", "pieces": "24", "minifigs": null, "image": "https://images.brickset.com/sets/small/4310-1.jpg?200801240224", "community": "233 own this set", "needs": ", 135 want it", "buy_at": "Amazon", "buy_at2": "Amazon", "buy_at3": "eBay", "buy_at4": "BrickLink"},
{"name": "Black Robot Pod", "pieces": "50", "minifigs": null, "image": "https://images.brickset.com/sets/small/4335-1.jpg?200408310950", "community": "578 own this set", "needs": ", 292 want it", "buy_at": "Amazon", "buy_at2": "Amazon", "buy_at3": "eBay", "buy_at4": "BrickLink"},
{"name": "Robo Pod", "pieces": "Yes", "minifigs": null, "image": "https://images.brickset.com/sets/small/4346-1.jpg?200312170832", "community": "1856 own this set", "needs": ", 227 want it", "buy_at": "Amazon", "buy_at2": "Amazon", "buy_at3": "eBay", "buy_at4": "BrickLink"},
{"name": "Robo Pod", "pieces": null, "minifigs": null, "image": "/assets/images/misc/blankbox.gif", "community": "43 own this set", "needs": ", 65 want it", "buy_at": "Amazon", "buy_at2": "Amazon", "buy_at3": "eBay", "buy_at4": "BrickLink"},
{"name": "Auto Pod", "pieces": "Yes", "minifigs": null, "image": "https://images.brickset.com/sets/small/4347-1.jpg?200312170833", "community": "1762 own this set", "needs": ", 180 want it", "buy_at": "Amazon", "buy_at2": "Amazon", "buy_at3": "eBay", "buy_at4": "BrickLink"},
{"name": "Auto Pod", "pieces": null, "minifigs": null, "image": "/assets/images/misc/blankbox.gif", "community": "46 own this set", "needs": ", 56 want it", "buy_at": "Amazon", "buy_at2": "Amazon", "buy_at3": "eBay", "buy_at4": "BrickLink"},
{"name": "Aero Pod", "pieces": "Yes", "minifigs": null, "image": "https://images.brickset.com/sets/small/4348-1.jpg?200312170833", "community": "1990 own this set", "needs": ", 191 want it", "buy_at": "Amazon", "buy_at2": "Amazon", "buy_at3": "eBay", "buy_at4": "BrickLink"},
{"name": "Aero Pod", "pieces": null, "minifigs": null, "image": "/assets/images/misc/blankbox.gif", "community": "39 own this set", "needs": ", 56 want it", "buy_at": "Amazon", "buy_at2": "Amazon", "buy_at3": "eBay", "buy_at4": "BrickLink"},
{"name": "Wild Pod", "pieces": "Yes", "minifigs": null, "image": "https://images.brickset.com/sets/small/4349-1.jpg?200312170834", "community": "1800 own this set", "needs": ", 195 want it", "buy_at": "Amazon", "buy_at2": "Amazon", "buy_at3": "eBay", "buy_at4": "BrickLink"},
{"name": "Wild Pod", "pieces": null, "minifigs": null, "image": "/assets/images/misc/blankbox.gif", "community": "30 own this set", "needs": ", 51 want it", "buy_at": "Amazon", "buy_at2": "Amazon", "buy_at3": "eBay", "buy_at4": "BrickLink"},
{"name": "Buildings", "pieces": "506", "minifigs": null, "image": "https://images.brickset.com/sets/small/4406-1.jpg?201512021051", "community": "167 own this set", "needs": ", 110 want it", "buy_at": "Amazon", "buy_at2": "Amazon", "buy_at3": "eBay", "buy_at4": "BrickLink"}
]