[
{"name": "Pneumatic Crane Truck", "pieces": "862", "minifigs": null, "image": "https://images.brickset.com/sets/small/8431-1.jpg?200206220211", "community": "520 own this set", "needs": ", 463 want it", "buy_at": "Amazon", "buy_at2": "Amazon", "buy_at3": "eBay", "buy_at4": "BrickLink"},
{"name": "Williams F1 Team Racer", "pieces": "1484", "minifigs": null, "image": "https://images.brickset.com/sets/small/8461-1.jpg?200208030949", "community": "1152 own this set", "needs": ", 1155 want it", "buy_at": "Amazon", "buy_at2": "Amazon", "buy_at3": "eBay", "buy_at4": "BrickLink"},
{"name": "Power Crusher", "pieces": "92", "minifigs": null, "image": "https://images.brickset.com/sets/small/8468-1.jpg?200112161200", "community": "565 own this set", "needs": ", 120 want it", "buy_at": "Amazon", "buy_at2": "Amazon", "buy_at3": "eBay", "buy_at4": "BrickLink"},
{"name": "Slammer Raptor", "pieces": "144", "minifigs": null, "image": "https://images.brickset.com/sets/small/8469-1.jpg?200112121200", "community": "755 own this set", "needs": ", 122 want it", "buy_at": "Amazon", "buy_at2": "Amazon", "buy_at3": "eBay", "buy_at4": "BrickLink"},
{"name": "Slammer G-Force", "pieces": "148", "minifigs": null, "image": "https://images.brickset.com/sets/small/8470-1.jpg?200112121200", "community": "431 own this set", "needs": ", 125 want it", "buy_at": "Amazon", "buy_at2": "Amazon", "buy_at3": "eBay", "buy_at4": "BrickLink"},
{"name": "Nitro Burner", "pieces": "119", "minifigs": null, "image": "https://images.brickset.com/sets/small/8471-1.jpg?200112121200", "community": "364 own this set", "needs": ", 113 want it", "buy_at": "Amazon", "buy_at2": "Amazon", "buy_at3": "eBay", "buy_at4": "BrickLink"},
{"name": "Street 'n' Mud Racer", "pieces": "347", "minifigs": null, "image": "https://images.brickset.com/sets/small/8472-1.jpg?200201071200", "community": "225 own this set", "needs": ", 153 want it", "buy_at": "Amazon", "buy_at2": "Amazon", "buy_at3": "eBay", "buy_at4": "BrickLink"},
{"name": "Nitro Race Team", "pieces": "500", "minifigs": null, "image": "https://images.brickset.com/sets/small/8473-1.jpg?200112121200", "community": "337 own this set", "needs": ", 133 want it", "buy_at": "Amazon", "buy_at2": "Amazon", "buy_at3": "eBay", "buy_at4": "BrickLink"},
{"name": "RC Race Buggy", "pieces": "283", "minifigs": null, "image": "https://images.brickset.com/sets/small/8475-1.jpg?200112121200", "community": "360 own this set", "needs": ", 264 want it", "buy_at": "Amazon", "buy_at2": "Amazon", "buy_at3": "eBay", "buy_at4": "BrickLink"},
{"name": "Gahlok Va", "pieces": "26", "minifigs": null, "image": "https://images.brickset.com/sets/small/8550-1.jpg?200201191200", "community": "1477 own this set", "needs": ", 388 want it", "buy_at": "Amazon", "buy_at2": "Amazon", "buy_at3": "eBay", "buy_at4": "BrickLink"},
{"name": "Kohrak Va", "pieces": "28", "minifigs": null, "image": "https://images.brickset.com/sets/small/8551-1.jpg?200201191200", "community": "1520 own this set", "needs": ", 421 want it", "buy_at": "Amazon", "buy_at2": "Amazon", "buy_at3": "eBay", "buy_at4": "BrickLink"},
{"name": "Lehvak Va", "pieces": "28", "minifigs": null, "image": "https://images.brickset.com/sets/small/8552-1.jpg?200201191200", "community": "1426 own this set", "needs": ", 428 want it", "buy_at": "Amazon", "buy_at2": "Amazon", "buy_at3": "eBay", "buy_at4": "BrickLink"},
{"name": "Pahrak Va", "pieces": "27", "minifigs": null, "image": "https://images.brickset.com/sets/small/8553-1.jpg?200201191200", "community": "1470 own this set", "needs": ", 411 want it", "buy_at": "Amazon", "buy_at2": "Amazon", "buy_at3": "eBay", "buy_at4": "BrickLink"},
{"name": "Tahnok Va", "pieces": "27", "minifigs": null, "image": "https://images.brickset.com/sets/small/8554-1.jpg?200201191200", "community": "1447 own this set", "needs": ", 419 want it", "buy_at": "Amazon", "buy_at2": "Amazon", "buy_at3": "eBay", "buy_at4": "BrickLink"},
{"name": "Nuhvok Va", "pieces": "26", "minifigs": null, "image": "https://images.brickset.com/sets/small/8555-1.jpg?200201191200", "community": "1430 own this set", "needs": ", 421 want it", "buy_at": "Amazon", "buy_at2": "Amazon", "buy_at3": "eBay", "buy_at4": "BrickLink"},
{"name": "Boxor Vehicle", "pieces": "157", "minifigs": null, "image": "https://images.brickset.com/sets/small/8556-1.jpg?200112121200", "community": "1371 own this set", "needs": ", 572 want it", "buy_at": "Amazon", "buy_at2": "Amazon", "buy_at3": "eBay", "buy_at4": "BrickLink"},
{"name": "Exo-Toa", "pieces": "378", "minifigs": null, "image": "https://images.brickset.com/sets/small/8557-1.jpg?200112121200", "community": "1193 own this set", "needs": ", 709 want it", "buy_at": "Amazon", "buy_at2": "Amazon", "buy_at3": "eBay", "buy_at4": "BrickLink"},
{"name": "Cahdok and Gahdok", "pieces": "636", "minifigs": null, "image": "https://images.brickset.com/sets/small/8558-1.jpg?200112121200", "community": "771 own this set", "needs": ", 726 want it", "buy_at": "Amazon", "buy_at2": "Amazon", "buy_at3": "eBay", "buy_at4": "BrickLink"},
{"name": "Krana", "pieces": null, "minifigs": null, "image": "https://images.brickset.com/sets/small/8559-1.jpg?200709270216", "community": "630 own this set", "needs": ", 282 want it", "buy_at": "Amazon", "buy_at2": "Amazon", "buy_at3": "eBay", "buy_at4": "BrickLink"},
{"name": "Pahrak", "pieces": "41", "minifigs": null, "image": "https://images.brickset.com/sets/small/8560-1.jpg?200110301200", "community": "3432 own this set", "needs": ", 470 want it", "buy_at": "Amazon", "buy_at2": "Amazon", "buy_at3": "eBay", "buy_at4": "BrickLink"},
{"name": "Nuhvok", "pieces": "41", "minifigs": null, "image": "https://images.brickset.com/sets/small/8561-1.jpg?200110301200", "community": "3392 own this set", "needs": ", 491 want it", "buy_at": "Amazon", "buy_at2": "Amazon", "buy_at3": "eBay", "buy_at4": "BrickLink"},
{"name": "Gahlok", "pieces": "41", "minifigs": null, "image": "https://images.brickset.com/sets/small/8562-1.jpg?200110301200", "community": "3365 own this set", "needs": ", 482 want it", "buy_at": "Amazon", "buy_at2": "Amazon", "buy_at3": "eBay", "buy_at4": "BrickLink"},
{"name": "Tahnok", "pieces": "41", "minifigs": null, "image": "https://images.brickset.com/sets/small/8563-1.jpg?200110301200", "community": "3464 own this set", "needs": ", 526 want it", "buy_at": "Amazon", "buy_at2": "Amazon", "buy_at3": "eBay", "buy_at4": "BrickLink"},
{"name": "Lehvak", "pieces": "41", "minifigs": null, "image": "https://images.brickset.com/sets/small/8564-1.jpg?200110301200", "community": "3500 own this set", "needs": ", 464 want it", "buy_at": "Amazon", "buy_at2": "Amazon", "buy_at3": "eBay", "buy_at4": "BrickLink"},
{"name": "Kohrak", "pieces": "41", "minifigs": null, "image": "https://images.brickset.com/sets/small/8565-1.jpg?200110301200", "community": "3351 own this set", "needs": ", 524 want it", "buy_at": "Amazon", "buy_at2": "Amazon", "buy_at3": "eBay", "buy_at4": "BrickLink"}
]