[
{"name": "Solo Sub", "pieces": "25", "minifigs": "1", "image": "https://images.brickset.com/sets/small/6110-1.jpg", "community": "2071 own this set", "needs": ", 445 want it", "buy_at": "Amazon", "buy_at2": "Amazon", "buy_at3": "eBay", "buy_at4": "BrickLink"},
{"name": "Crab", "pieces": "78", "minifigs": "1", "image": "https://images.brickset.com/sets/small/6140-1.jpg", "community": "764 own this set", "needs": ", 365 want it", "buy_at": "Amazon", "buy_at2": "Amazon", "buy_at3": "eBay", "buy_at4": "BrickLink"},
{"name": "Crystal Detector", "pieces": "104", "minifigs": "1", "image": "https://images.brickset.com/sets/small/6150-1.jpg", "community": "776 own this set", "needs": ", 526 want it", "buy_at": "Amazon", "buy_at2": "Amazon", "buy_at3": "eBay", "buy_at4": "BrickLink"},
{"name": "Crystal Detector", "pieces": "1", "minifigs": "1", "image": "https://images.brickset.com/sets/small/6159-1.jpg?200506101201", "community": "180 own this set", "needs": ", 322 want it", "buy_at": "Amazon", "buy_at2": "Amazon", "buy_at3": "eBay", "buy_at4": "BrickLink"},
{"name": "Sea Scorpion", "pieces": "301", "minifigs": "3", "image": "https://images.brickset.com/sets/small/6160-1.jpg", "community": "1061 own this set", "needs": ", 668 want it", "buy_at": "Amazon", "buy_at2": "Amazon", "buy_at3": "eBay", "buy_at4": "BrickLink"},
{"name": "Hydro Search Sub", "pieces": "297", "minifigs": "4", "image": "https://images.brickset.com/sets/small/6180-1.jpg", "community": "767 own this set", "needs": ", 740 want it", "buy_at": "Amazon", "buy_at2": "Amazon", "buy_at3": "eBay", "buy_at4": "BrickLink"},
{"name": "Stingray Stormer", "pieces": "408", "minifigs": "4", "image": "https://images.brickset.com/sets/small/6198-1.jpg", "community": "686 own this set", "needs": ", 827 want it", "buy_at": "Amazon", "buy_at2": "Amazon", "buy_at3": "eBay", "buy_at4": "BrickLink"},
{"name": "Hydro Crystallisation Station", "pieces": "482", "minifigs": "5", "image": "https://images.brickset.com/sets/small/6199-1.jpg", "community": "585 own this set", "needs": ", 968 want it", "buy_at": "Amazon", "buy_at2": "Amazon", "buy_at3": "eBay", "buy_at4": "BrickLink"},
{"name": "Chopper Cop", "pieces": "17", "minifigs": "1", "image": "https://images.brickset.com/sets/small/6324-1.jpg", "community": "2498 own this set", "needs": ", 202 want it", "buy_at": "Amazon", "buy_at2": "Amazon", "buy_at3": "eBay", "buy_at4": "BrickLink"},
{"name": "Package Pick-Up", "pieces": "28", "minifigs": "1", "image": "https://images.brickset.com/sets/small/6325-1.jpg", "community": "1404 own this set", "needs": ", 278 want it", "buy_at": "Amazon", "buy_at2": "Amazon", "buy_at3": "eBay", "buy_at4": "BrickLink"},
{"name": "Town Folk", "pieces": "35", "minifigs": "6", "image": "https://images.brickset.com/sets/small/6326-1.jpg", "community": "1077 own this set", "needs": ", 405 want it", "buy_at": "Amazon", "buy_at2": "Amazon", "buy_at3": "eBay", "buy_at4": "BrickLink"},
{"name": "Turbo Champ", "pieces": "48", "minifigs": "2", "image": "https://images.brickset.com/sets/small/6327-1.jpg", "community": "1264 own this set", "needs": ", 199 want it", "buy_at": "Amazon", "buy_at2": "Amazon", "buy_at3": "eBay", "buy_at4": "BrickLink"},
{"name": "Helicopter Transport", "pieces": "102", "minifigs": "2", "image": "https://images.brickset.com/sets/small/6328-1.jpg", "community": "1330 own this set", "needs": ", 337 want it", "buy_at": "Amazon", "buy_at2": "Amazon", "buy_at3": "eBay", "buy_at4": "BrickLink"},
{"name": "Truck Stop", "pieces": "137", "minifigs": "3", "image": "https://images.brickset.com/sets/small/6329-1.jpg", "community": "484 own this set", "needs": ", 366 want it", "buy_at": "Amazon", "buy_at2": "Amazon", "buy_at3": "eBay", "buy_at4": "BrickLink"},
{"name": "Cargo Center", "pieces": "242", "minifigs": "5", "image": "https://images.brickset.com/sets/small/6330-1.jpg", "community": "347 own this set", "needs": ", 451 want it", "buy_at": "Amazon", "buy_at2": "Amazon", "buy_at3": "eBay", "buy_at4": "BrickLink"},
{"name": "Command Post Central", "pieces": "272", "minifigs": "7", "image": "https://images.brickset.com/sets/small/6332-1.jpg", "community": "1070 own this set", "needs": ", 481 want it", "buy_at": "Amazon", "buy_at2": "Amazon", "buy_at3": "eBay", "buy_at4": "BrickLink"},
{"name": "Race and Chase", "pieces": "50", "minifigs": "2", "image": "https://images.brickset.com/sets/small/6333-1.jpg", "community": "372 own this set", "needs": ", 178 want it", "buy_at": "Amazon", "buy_at2": "Amazon", "buy_at3": "eBay", "buy_at4": "BrickLink"},
{"name": "Res-Q Jet-Ski", "pieces": "18", "minifigs": "1", "image": "https://images.brickset.com/sets/small/6415-1.jpg", "community": "1424 own this set", "needs": ", 244 want it", "buy_at": "Amazon", "buy_at2": "Amazon", "buy_at3": "eBay", "buy_at4": "BrickLink"},
{"name": "Mail Carrier", "pieces": "12", "minifigs": "1", "image": "https://images.brickset.com/sets/small/6420-1.jpg", "community": "1392 own this set", "needs": ", 692 want it", "buy_at": "Amazon", "buy_at2": "Amazon", "buy_at3": "eBay", "buy_at4": "BrickLink"},
{"name": "Telephone Repair", "pieces": "43", "minifigs": "1", "image": "https://images.brickset.com/sets/small/6422-1.jpg", "community": "1461 own this set", "needs": ", 389 want it", "buy_at": "Amazon", "buy_at2": "Amazon", "buy_at3": "eBay", "buy_at4": "BrickLink"},
{"name": "Rig Racers", "pieces": "101", "minifigs": "3", "image": "https://images.brickset.com/sets/small/6424-1.jpg", "community": "472 own this set", "needs": ", 222 want it", "buy_at": "Amazon", "buy_at2": "Amazon", "buy_at3": "eBay", "buy_at4": "BrickLink"},
{"name": "Super Cycle Center", "pieces": "137", "minifigs": "4", "image": "https://images.brickset.com/sets/small/6426-1.jpg", "community": "825 own this set", "needs": ", 401 want it", "buy_at": "Amazon", "buy_at2": "Amazon", "buy_at3": "eBay", "buy_at4": "BrickLink"},
{"name": "Wave Saver", "pieces": "1", "minifigs": "1", "image": "https://images.brickset.com/sets/small/6428-1.jpg", "community": "447 own this set", "needs": ", 178 want it", "buy_at": "Amazon", "buy_at2": "Amazon", "buy_at3": "eBay", "buy_at4": "BrickLink"},
{"name": "Road Rescue", "pieces": "48", "minifigs": "1", "image": "https://images.brickset.com/sets/small/6431-1.jpg", "community": "2630 own this set", "needs": ", 346 want it", "buy_at": "Amazon", "buy_at2": "Amazon", "buy_at3": "eBay", "buy_at4": "BrickLink"},
{"name": "Emergency Evac", "pieces": "101", "minifigs": "1", "image": "https://images.brickset.com/sets/small/6445-1.jpg", "community": "3740 own this set", "needs": ", 388 want it", "buy_at": "Amazon", "buy_at2": "Amazon", "buy_at3": "eBay", "buy_at4": "BrickLink"}
]